py_netatmo_truetemp_cli/__init__.py
py_netatmo_truetemp_cli/__main__.py
py_netatmo_truetemp_cli/_version.py
py_netatmo_truetemp_cli/cli.py
py_netatmo_truetemp_cli/display.py
py_netatmo_truetemp_cli/helpers.py
py_netatmo_truetemp_cli/py.typed
py_netatmo_truetemp_cli-1.0.2.dist-info/METADATA
py_netatmo_truetemp_cli-1.0.2.dist-info/WHEEL
py_netatmo_truetemp_cli-1.0.2.dist-info/entry_points.txt
py_netatmo_truetemp_cli-1.0.2.dist-info/licenses/LICENSE
py_netatmo_truetemp_cli-1.0.2.dist-info/RECORD
