Metadata-Version: 2.4
Name: py-netatmo-truetemp-cli
Version: 1.0.2
Summary: Netatmo's missing true temperature CLI - set real room temps from your terminal
Project-URL: Homepage, https://github.com/py-netatmo-unofficial/py-netatmo-truetemp-cli
Project-URL: Repository, https://github.com/py-netatmo-unofficial/py-netatmo-truetemp-cli
Project-URL: Issues, https://github.com/py-netatmo-unofficial/py-netatmo-truetemp-cli/issues
Project-URL: Changelog, https://github.com/py-netatmo-unofficial/py-netatmo-truetemp-cli/blob/main/CHANGELOG.md
Project-URL: Documentation, https://github.com/py-netatmo-unofficial/py-netatmo-truetemp-cli#readme
Author-email: P4uLT <P4uLT@users.noreply.github.com>
Maintainer-email: P4uLT <P4uLT@users.noreply.github.com>
License: MIT
License-File: LICENSE
Keywords: automation,cli-tool,command-line,home-automation,netatmo,smart-home,temperature-control,terminal,thermostat,true-temperature,truetemp
Classifier: Development Status :: 5 - Production/Stable
Classifier: Environment :: Console
Classifier: Intended Audience :: Developers
Classifier: Intended Audience :: End Users/Desktop
Classifier: License :: OSI Approved :: MIT License
Classifier: Operating System :: OS Independent
Classifier: Programming Language :: Python :: 3
Classifier: Programming Language :: Python :: 3 :: Only
Classifier: Programming Language :: Python :: 3.13
Classifier: Topic :: Home Automation
Classifier: Topic :: Utilities
Classifier: Typing :: Typed
Requires-Python: >=3.13
Requires-Dist: py-netatmo-truetemp>=0.3.0
Requires-Dist: rich>=14.2.0
Requires-Dist: typer[all]>=0.9.0
